.gitignore
MANIFEST.in
README.rst
bootstrap.py
buildout.cfg
setup.py
collective/__init__.py
collective.portlet.socialnetworks.egg-info/PKG-INFO
collective.portlet.socialnetworks.egg-info/SOURCES.txt
collective.portlet.socialnetworks.egg-info/dependency_links.txt
collective.portlet.socialnetworks.egg-info/entry_points.txt
collective.portlet.socialnetworks.egg-info/namespace_packages.txt
collective.portlet.socialnetworks.egg-info/not-zip-safe
collective.portlet.socialnetworks.egg-info/requires.txt
collective.portlet.socialnetworks.egg-info/top_level.txt
collective/portlet/__init__.py
collective/portlet/socialnetworks/__init__.py
collective/portlet/socialnetworks/configure.zcml
collective/portlet/socialnetworks/rebuild_i18n.sh
collective/portlet/socialnetworks/socialnetworks.css
collective/portlet/socialnetworks/socialnetworks.pt
collective/portlet/socialnetworks/socialnetworks.py
collective/portlet/socialnetworks/testing.py
collective/portlet/socialnetworks/upgrades.py
collective/portlet/socialnetworks/upgrades.zcml
collective/portlet/socialnetworks/version.txt
collective/portlet/socialnetworks/locales/collective.portlet.socialnetworks.pot
collective/portlet/socialnetworks/locales/en/LC_MESSAGES/collective.portlet.socialnetworks.po
collective/portlet/socialnetworks/locales/fr/LC_MESSAGES/collective.portlet.socialnetworks.po
collective/portlet/socialnetworks/profiles/default/cssregistry.xml
collective/portlet/socialnetworks/profiles/default/metadata.xml
collective/portlet/socialnetworks/profiles/default/portlets.xml
collective/portlet/socialnetworks/profiles/default/registry.xml
collective/portlet/socialnetworks/resources/blogger.png
collective/portlet/socialnetworks/resources/digg.png
collective/portlet/socialnetworks/resources/facebook.png
collective/portlet/socialnetworks/resources/flickr.png
collective/portlet/socialnetworks/resources/googleplus.png
collective/portlet/socialnetworks/resources/linkedin.png
collective/portlet/socialnetworks/resources/myspace.png
collective/portlet/socialnetworks/resources/pinterest.png
collective/portlet/socialnetworks/resources/rss.png
collective/portlet/socialnetworks/resources/stumbleupon.png
collective/portlet/socialnetworks/resources/tumblr.png
collective/portlet/socialnetworks/resources/twitter.png
collective/portlet/socialnetworks/resources/vimeo.png
collective/portlet/socialnetworks/resources/youtube.png
collective/portlet/socialnetworks/tests/__init__.py
